{
  "@context":"http://schema.org/",
  "@id":"",
  "@type":"Book",
  "bookEdition":"",
  "bookFormat":"",
  "illustrator":"",
  "isbn":"",
  "numberOfPages":"",
  "about":"",
  "accessMode":"",
  "assessibilitySummary":"",
  "author":"",
  "contributor":"",
  "copyrightHolder":"",
  "copyrightYear":"",
  "creator":"",
  "dateCreated":"",
  "datePublished":"",
  "editor":"",
  "genre":"",
  "inLanguage":"",
  "keywords":"",
  "provider":"",
  "publisher":"",
  "translator":"",
  "thumbnailUrl":"",
  "name":"",
  "image":"",
  "identifier":""
  }
